src/coda/_version.py
helix_coda-0.1.dev1.dist-info/METADATA
helix_coda-0.1.dev1.dist-info/WHEEL
helix_coda-0.1.dev1.dist-info/entry_points.txt
helix_coda-0.1.dev1.dist-info/licenses/LICENSE
helix_coda-0.1.dev1.dist-info/RECORD
