Metadata-Version: 2.4
Name: helix-coda
Version: 0.1.dev1
Summary: Code indexing for better AI code generation
License-File: LICENSE
Requires-Python: >=3.11
Requires-Dist: asgi-correlation-id>=4.3.4
Requires-Dist: better-exceptions>=0.3.3
Requires-Dist: click>=8.1.8
Requires-Dist: colorama>=0.4.6
Requires-Dist: dotenv>=0.9.9
Requires-Dist: fastapi[standard]>=0.115.12
Requires-Dist: httpx-retries>=0.3.2
Requires-Dist: httpx>=0.28.1
Requires-Dist: mcp>=1.6.0
Requires-Dist: posthog>=4.0.1
Requires-Dist: structlog>=25.3.0
